[
    {
        "af": 4,
        "avg": 186.07095,
        "dst_addr": "82.213.28.12",
        "dst_name": "82.213.28.12",
        "dup": 0,
        "from": "78.100.92.24",
        "fw": 4970,
        "group_id": 20969445,
        "lts": 30,
        "max": 187.315775,
        "min": 185.37316,
        "msm_id": 20969445,
        "msm_name": "Ping",
        "prb_id": 29275,
        "proto": "ICMP",
        "rcvd": 3,
        "result": [
            {
                "rtt": 187.315775
            },
            {
                "rtt": 185.523915
            },
            {
                "rtt": 185.37316
            }
        ],
        "sent": 3,
        "size": 64,
        "src_addr": "10.92.54.177",
        "step": 10800,
        "stored_timestamp": 1556199609,
        "timestamp": 1556199466,
        "ttl": 47,
        "type": "ping"
    },
    {
        "af": 4,
        "avg": 185.5511983333,
        "dst_addr": "82.213.28.12",
        "dst_name": "82.213.28.12",
        "dup": 0,
        "from": "82.148.114.58",
        "fw": 4970,
        "group_id": 20969445,
        "lts": 32,
        "max": 185.956002,
        "min": 185.320697,
        "msm_id": 20969445,
        "msm_name": "Ping",
        "prb_id": 6090,
        "proto": "ICMP",
        "rcvd": 3,
        "result": [
            {
                "rtt": 185.956002
            },
            {
                "rtt": 185.320697
            },
            {
                "rtt": 185.376896
            }
        ],
        "sent": 3,
        "size": 64,
        "src_addr": "82.148.114.58",
        "step": 10800,
        "stored_timestamp": 1556199762,
        "timestamp": 1556199722,
        "ttl": 51,
        "type": "ping"
    }
]